encryption/permutation.v
module permutation (
    input              clk,
    input              rst,
    input      [319:0] S,
    input      [4:0]   round,
    input              start,
    output reg [319:0] S_out,
    output reg         fin  
);

reg [63:0] x0, x1, x2, x3, x4;
reg [63:0] x2_pc;
reg [63:0] x0_ps, x1_ps, x2_ps, x3_ps, x4_ps;
reg [4:0] counter;
integer i;

// FSM
reg [2:0]st, nst;
parameter IDLE = 'd0;
parameter IN   = 'd1;
parameter PC   = 'd2;
parameter PS   = 'd3;
parameter PL   = 'd4;
parameter OUT  = 'd5;

always @(posedge clk) begin
    if (rst) st <= IDLE;
    else     st <= nst;
end

always @(*) begin
    case(st) 
        IDLE: nst = (start)?IN:IDLE;
        IN:   nst = PC;
        PC:   nst = PS;
        PS:   nst = PL;
        PL:   nst = (counter==round)? OUT : PC ;
        OUT:  nst = IDLE;
        default: nst = IDLE;
    endcase
end

wire [63:0] Cr [11:0];
    assign Cr[0] = 64'hf0;
    assign Cr[1] = 64'he1;
    assign Cr[2] = 64'hd2;
    assign Cr[3] = 64'hc3;
    assign Cr[4] = 64'hb4;
    assign Cr[5] = 64'ha5;
    assign Cr[6] = 64'h96;
    assign Cr[7] = 64'h87;
    assign Cr[8] = 64'h78;
    assign Cr[9] = 64'h69;
    assign Cr[10] = 64'h5a;
    assign Cr[11] = 64'h4b;
wire [4:0] const[31:0];
    assign const[0]  = 5'h4;
    assign const[1]  = 5'hb;
    assign const[2]  = 5'h1f;
    assign const[3]  = 5'h14;
    assign const[4]  = 5'h1a;
    assign const[5]  = 5'h15;
    assign const[6]  = 5'h9;
    assign const[7]  = 5'h2;
    assign const[8]  = 5'h1b;
    assign const[9]  = 5'h5;
    assign const[10] = 5'h8;
    assign const[11] = 5'h12;
    assign const[12] = 5'h1d;
    assign const[13] = 5'h3;
    assign const[14] = 5'h6;
    assign const[15] = 5'h1c;
    assign const[16] = 5'h1e;
    assign const[17] = 5'h13;
    assign const[18] = 5'h7;
    assign const[19] = 5'he;
    assign const[20] = 5'h0;
    assign const[21] = 5'hd;
    assign const[22] = 5'h11;
    assign const[23] = 5'h18;
    assign const[24] = 5'h10;
    assign const[25] = 5'hc;
    assign const[26] = 5'h1;
    assign const[27] = 5'h19;
    assign const[28] = 5'h16;
    assign const[29] = 5'ha;
    assign const[30] = 5'hf;
    assign const[31] = 5'h17;

always @(posedge clk) begin
    if (rst) counter <= 5'd0;
    else if (st == IDLE) counter <= 5'd0;
    else if (st==PC) begin
        if (counter < round) counter <= counter +1'b1;
        else counter <= counter; 
    end 
    else counter <= counter;
end

always @(posedge clk or posedge rst) begin
    if (rst) begin
        {x0, x1, x2, x3, x4, x2_pc} <= 64'd0;
        {x0_ps, x1_ps, x2_ps, x3_ps, x4_ps} <= 64'd0;
        S_out <= 320'd0;
    end 
    else begin
        case (st)
        IN: begin
            {x0, x1, x2, x3, x4} <= S; // S = x0 || x1 || x2 || x3 || x4 
            {x0_ps, x1_ps, x2_ps, x3_ps, x4_ps} <= 64'd0;
        end 
        PC: begin
            if (round == 5'd12)     x2_pc <= x2 ^ Cr[counter];
            else if (round == 5'd8) x2_pc <= x2 ^ Cr[counter+5'd4];
            else if (round == 5'd6) x2_pc <= x2 ^ Cr[counter+5'd6];
            else x2_pc <= x2_pc;
        end
        PS: begin
            for (i=0;i<64;i=i+1) begin
            {x0_ps[i], x1_ps[i], x2_ps[i], x3_ps[i], x4_ps[i]} <= const[{x0[i], x1[i], x2_pc[i], x3[i], x4[i]}];
            end
        end
        PL: begin
            x0 <= x0_ps ^ (x0_ps >> 19) ^ (x0_ps >> 28) ^ (x0_ps << (64 - 19)) ^ (x0_ps << (64 - 28));
            x1 <= x1_ps ^ (x1_ps >> 61) ^ (x1_ps >> 39) ^ (x1_ps << (64 - 61)) ^ (x1_ps << (64 - 39));
            x2 <= x2_ps ^ (x2_ps >> 1)  ^ (x2_ps >> 6)  ^ (x2_ps << (64 - 1))  ^ (x2_ps << (64 - 6));
            x3 <= x3_ps ^ (x3_ps >> 10) ^ (x3_ps >> 17) ^ (x3_ps << (64 - 10)) ^ (x3_ps << (64 - 17));
            x4 <= x4_ps ^ (x4_ps >> 7)  ^ (x4_ps >> 41) ^ (x4_ps << (64 - 7))  ^ (x4_ps << (64 - 41));
        end
        OUT: begin
            S_out <= {x0, x1, x2, x3, x4};
        end
        default: begin
            x0 <= x0;
            x1 <= x1;
            x2 <= x2;
            x3 <= x3;
            x4 <= x4;
            x2_pc <= x2_pc;
            x0_ps <= x0_ps;
            x1_ps <= x1_ps;
            x2_ps <= x2_ps;
            x3_ps <= x3_ps;
            x4_ps <= x4_ps;
        end
    endcase
    end
end

// signal done
always @(posedge clk or posedge rst) begin
    if (rst) fin <=1'd0;
    else if (st==OUT) fin <=1'd1;
    else fin <=1'd0;
end


endmodule

encryption/encryption.v
module encryption #(
    parameter k = 128,   // Key size
    parameter r = 64,    // Rate
    parameter a = 12,    // Initialization and finalization round number
    parameter b = 6,     // Intermediate round number
    parameter al = 40,   // Associated data length (ASCON example)
    parameter pl = 40   // Plaintext length (ascon example)
)(
    input clk, 
    input rst,
    input [k-1:0] key,
    input [127:0] nonce,
    input [al-1:0] ad, // Associated data
    input [pl-1:0] pt, // Plaintext
    input encryption_start,

    output [pl-1:0] ct, // Ciphertext
    output [127:0] tag, // Authentication tag
    output encryption_fin,
    output reg [319:0] ini_stemp, ad_stemp, pt_stemp
);

// Internal Registers and Wires
reg  [319:0] S;      // State register
reg  [319:0] Pin;
wire [319:0] Pout;  // Permutation output
reg  [319:0] Pout_r; 
reg  [pl-1:0] ct_r;
reg  [127:0] tag_r;
reg  permutation_start;  // Permutation start signal
wire permutation_fin;    // Permutation done signal
reg  [3:0] block_counter;
reg  [4:0] round;    // Round counter

// FSM State Encoding
reg [3:0] state, n_state;
parameter IDLE            = 4'd0;
parameter INITIALIZE      = 4'd1;
parameter ASSOCIATED_DATA = 4'd2;
parameter PLAINTEXT       = 4'd3;
parameter FINALIZE        = 4'd4;
parameter FIN             = 4'd5;

// Initialization Vector
parameter c    = 320 - r; // Capacity
parameter IV   = 64'h80800c0800000000;
wire [r-1:0] Sr;         // Rate part of the state
wire [c-1:0] Sc;         // Capacity part of the state
assign {Sr, Sc} = S;

// Padding calculations for associated data and plaintext
wire [3:0] s,t;

parameter ad_z = ((al+1)%r != 0) ? (r-((al+1)%r)) : 0;
parameter AL   = al + 1 + ad_z;
assign    s    = (AL / r) ; // Associated data blocks // block length =  r

parameter pt_z = ((pl+1)%r != 0) ? (r-((pl+1)%r)) : 0;
parameter PL   = pl + 1 + pt_z;
assign    t    = (PL / r) ; // Plaintext blocks

wire [AL-1:0] A;
wire [PL-1:0] P;
assign A = {ad, 1'b1, {ad_z{1'b0}}};
assign P = {pt, 1'b1, {pt_z{1'b0}}};


// State Transition
always @(posedge clk or posedge rst) begin
    if (rst) state <= IDLE;
    else     state <= n_state;
end

// Next State Logic
always @(*) begin
    case (state) 
        IDLE:            n_state = (encryption_start) ? INITIALIZE : IDLE;
        INITIALIZE:      n_state = (in_finish) ? ASSOCIATED_DATA : INITIALIZE;
        ASSOCIATED_DATA: n_state = (block_counter == s) ? PLAINTEXT : ASSOCIATED_DATA;
        PLAINTEXT:       n_state = (pt_finish) ? FINALIZE : PLAINTEXT;
        FINALIZE:        n_state = (fin_finish) ? FIN : FINALIZE;
        FIN:             n_state = IDLE;
        default:         n_state = IDLE;
    endcase
end

always @(*) begin
    case(state)
        IDLE:            round = 0;
        INITIALIZE:      round = a;
        ASSOCIATED_DATA: round = b;
        PLAINTEXT:       round = b;
        FINALIZE:        round = a;
        FIN:             round = 0;
        default:         round = 0;
    endcase
end

//block_counter
always @(posedge clk) begin
    if (rst) begin
        block_counter <= 'd0;
    end
    else if (state == ASSOCIATED_DATA) begin
        if ((block_counter == s))   block_counter <= 'd0;
        else if ((block_counter < s) &&(permutation_fin))   block_counter <= block_counter +1'b1;
        else                        block_counter <= block_counter;
    end
    else if (state == PLAINTEXT) begin
        if ((block_counter == t-1) && (permutation_fin)) block_counter <= 'd0;
        else if ((block_counter < t-1) &&(permutation_fin)) block_counter <= block_counter + 1'b1;
        else                           block_counter <= block_counter;
    end
    else block_counter <= block_counter;
end

reg in_finish, as_finish,pt_finish,permutation_extend,fin_finish;
always @(posedge clk) begin
    if (rst) in_finish <= 1'b0;
    else if ((state == INITIALIZE) && (permutation_extend)) in_finish <= 1'b1;
    else in_finish <= 1'b0;
end
always @(posedge clk) begin
    if(rst) as_finish <= 1'b0;
    else if ((state == ASSOCIATED_DATA) && (block_counter == s)) as_finish <= 1'b1;
    else as_finish <= 1'b0;
end
always @(posedge clk) begin
    if(rst) pt_finish <= 1'b0;
    else if ((state == PLAINTEXT) && (t==1)) pt_finish <= 1'b1;
    else if ((state == PLAINTEXT) && (!permutation_start) && (block_counter == t-1)) pt_finish <= 1'b1;
    else pt_finish <= 1'b0;
end
always @(posedge clk) begin
    if(rst) permutation_extend <= 1'b0;
    else if (permutation_fin) permutation_extend <= 1'b1;
    else permutation_extend <= 1'b0;
end
always @(posedge clk) begin
    if (rst) fin_finish <= 1'b0;
    else if ((state == FINALIZE) && (permutation_extend)) fin_finish <= 1'b1;
    else fin_finish <= 1'b0;
end



// State Actions
always @(posedge clk or posedge rst) begin
    if (rst) begin
        S     <= 320'd0;
        Pin   <= 320'd0;
        Pout_r <= 320'd0;
        round <= 5'd0;
        permutation_start <= 1'b0;
        ct_r    <= 0;
        tag_r <= 0;
        permutation_extend <=1'b0;
        {ini_stemp, ad_stemp, pt_stemp} <= 960'b0;
    end 
    else begin
        case (state)
            IDLE: begin
                S <= {IV, key, nonce};
                permutation_start <= 1'b0;
                round <= 5'd0;
                tag_r <= 128'd0;
            end

            INITIALIZE: begin
                if (in_finish) begin
                    //P 後
                    S <= Pout_r ^ {{(320-k){1'b0}}, key};
                    permutation_start <= 1'b0; 
                    ini_stemp <= S;
                end 
                else begin
                    //P 前
                    Pin <= S;
                    permutation_start <= 1'b1;
                end
            end

            ASSOCIATED_DATA: begin
                if ((!permutation_start)&&(block_counter < s)) begin
                    // 第一次：設定 Pin 和啟動 permutation
                    Pin <= {(Sr ^ A[AL-1-(block_counter*r)-:r]), Sc};
                    permutation_start <= 1'b1;
                end
                else if ((permutation_extend)&&(block_counter < s)) begin
                    // 第1~(S-1)次     
                    S <= Pout_r;
                    Pin <= {Sr ^ A[AL-1-(block_counter*r)-:r], Sc};
                    permutation_start <= 1'b1;
                end
                else if ((permutation_extend)&&(block_counter == s)) begin
                    S <= Pout_r ^ {{319{1'b0}}, 1'b1};
                    permutation_start <= 1'b0;
                    ad_stemp <= S;
                end
            end
                
            PLAINTEXT: begin
                if (t==1) begin
                    ct_r[PL-1-(block_counter*r) -: r] <= Sr ^ P[PL-1-(block_counter*r) -: r];
                    S <= {Sr ^ P[PL-1-(block_counter*r) -: r] , Sc};
                    pt_stemp <= S;
                end
                // 第一次
                else if ((block_counter < t-1) && (!permutation_start) )begin
                    ct_r[PL-1-(block_counter*r) -: r] <= Sr ^ P[PL-1-(block_counter*r) -: r];
                    Pin <= { Sr ^ P[PL-1-(block_counter*r) -: r] , Sc};
                    permutation_start <=1'b1;
                end
                // 第2～(t-1)次
                else if ((block_counter < t-1) && (permutation_extend) ) begin
                    S <= Pout_r;
                    ct_r[PL-1-(block_counter*r) -: r] <= Sr ^ P[PL-1-(block_counter*r) -: r];
                    Pin <=  {Sr ^ P[PL-1-(block_counter*r) -: r] , Sc};
                    permutation_start <=1'b1;
                end
                // 第 t 次
                else if ((block_counter == t-1) && (permutation_extend) ) begin
                    S <= Pout_r;
                    ct_r[PL-1-(block_counter*r) -: r] <= Sr ^ P[PL-1-(block_counter*r) -: r];
                    S <= {Sr ^ P[PL-1-(block_counter*r) -: r] , Sc}; 
                    permutation_start <=1'b0;
                    pt_stemp <= S;
                end
            end

            FINALIZE: begin
                if (permutation_extend) begin
                    S <= Pout_r;
                    tag_r <= Pout_r[127:0] ^ key;
                    permutation_start <= 1'b0;
                end 
                else begin
                    Pin <= S ^ {{r{1'b0}}, key, {(320-r-k){1'b0}}};
                    permutation_start <= 1'b1;
                end
            end
            default: begin
                S <= S;
                Pin <= Pin;
                Pout_r <= Pout_r;
                permutation_start <= 1'b0;
                ct_r <= ct_r;
                tag_r <= tag_r;
                permutation_extend <= 1'b0;
                ini_stemp <= ini_stemp;
                ad_stemp <= ad_stemp;
                pt_stemp <= pt_stemp;
            end
        endcase
    end
end

assign encryption_fin = (state == FIN);
assign ct  = ct_r;
assign tag = tag_r;

always @(posedge clk ) begin
    if (rst) Pout_r <= 319'd0;
    else Pout_r <= Pout;
end

// Instantiate Permutation Module
permutation permutation (
    .clk(clk),
    .rst(rst),
    .S(Pin),
    .start(permutation_start),
    .round(round),
    .S_out(Pout),
    .fin(permutation_fin)
);

endmodule

encryption/encryption_tb.v
`timescale 1ns / 1ns

module encryption_tb;
    reg clk;
    reg rst_n;
    reg start;
    reg [127:0] key;
    reg [127:0] nonce;
    reg [39:0] associated_data; 
    reg [39:0] plaintext;       
    wire encryption_fin;
    wire [39:0] ciphertext;
    wire [127:0] tag;
    wire [319:0] ini_stemp, ad_stemp, pt_stemp;

    // Timeout variable
    integer timeout;

    // Instantiate the encryption module
    encryption encryption (
        .clk(clk),
        .rst(rst_n),
        .encryption_start(start),
        .key(key),
        .nonce(nonce),
        .ad(associated_data),
        .pt(plaintext),
        .encryption_fin(encryption_fin),
        .ct(ciphertext),
        .tag(tag),
        .ini_stemp(ini_stemp),
        .ad_stemp(ad_stemp),
        .pt_stemp(pt_stemp)
    );

    // Clock generation
    initial begin
        clk = 0;
        forever #5 clk = ~clk; // 100 MHz clock
    end

    // Monitor State Transitions and Debugging Information
    always @(posedge clk) begin
    end

    // Test sequence
    initial begin
        rst_n = 0;
        start = 0;
        key = 128'hb7234a4db9fb8b7c2aa5735ebef1180c;
        nonce = 128'h8ebb295da81c74b58306d4e8362e2242;
        associated_data = 40'h4153434f4e; 
        plaintext = 40'h6173636f6e;

        #10;
        rst_n = 1;
        #10;
        start = 1;
        rst_n = 0;
        #10;
        start = 0;

        timeout = 0; 
        while (~encryption_fin && timeout < 100000) begin
            #10;  
            timeout = timeout + 10;  
        end
        $display("Key: %h", key);
        $display("Nonce: %h", nonce);
        $display("Associated Data: %h", associated_data);
        $display("Plaintext: %h", plaintext);
        $display("--------------------------------------------");       
        // Display results
        $display("S after initial: %h", ini_stemp);
        $display("S after ad: %h", ad_stemp);
        $display("S after pt: %h", pt_stemp);
        $display("--------------------------------------------"); 
        $display("Final Ciphertext: %h", ciphertext);
        $display("Final Tag: %h", tag);
        

        
        #100;
        $finish;
    end

    // VCD dump
    initial begin
        $dumpfile("encryption.vcd");
        $dumpvars(0, encryption_tb);
    end
endmodule

encryption/encryption.vcd
$date
	Tue Feb 11 19:34:12 2025
$end
$version
	Icarus Verilog
$end
$timescale
	1ns
$end
$scope module encryption_tb $end
$var wire 128 ! tag [127:0] $end
$var wire 320 " pt_stemp [319:0] $end
$var wire 320 # ini_stemp [319:0] $end
$var wire 1 $ encryption_fin $end
$var wire 40 % ciphertext [39:0] $end
$var wire 320 & ad_stemp [319:0] $end
$var reg 40 ' associated_data [39:0] $end
$var reg 1 ( clk $end
$var reg 128 ) key [127:0] $end
$var reg 128 * nonce [127:0] $end
$var reg 40 + plaintext [39:0] $end
$var reg 1 , rst_n $end
$var reg 1 - start $end
$var integer 32 . timeout [31:0] $end
$scope module encryption $end
$var wire 40 / ad [39:0] $end
$var wire 1 ( clk $end
$var wire 40 0 ct [39:0] $end
$var wire 1 - encryption_start $end
$var wire 128 1 key [127:0] $end
$var wire 128 2 nonce [127:0] $end
$var wire 40 3 pt [39:0] $end
$var wire 1 , rst $end
$var wire 4 4 s [3:0] $end
$var wire 4 5 t [3:0] $end
$var wire 128 6 tag [127:0] $end
$var wire 1 7 permutation_fin $end
$var wire 1 $ encryption_fin $end
$var wire 64 8 Sr [63:0] $end
$var wire 256 9 Sc [255:0] $end
$var wire 320 : Pout [319:0] $end
$var wire 64 ; P [63:0] $end
$var wire 64 < A [63:0] $end
$var reg 320 = Pin [319:0] $end
$var reg 320 > Pout_r [319:0] $end
$var reg 320 ? S [319:0] $end
$var reg 320 @ ad_stemp [319:0] $end
$var reg 1 A as_finish $end
$var reg 4 B block_counter [3:0] $end
$var reg 40 C ct_r [39:0] $end
$var reg 1 D fin_finish $end
$var reg 1 E in_finish $end
$var reg 320 F ini_stemp [319:0] $end
$var reg 4 G n_state [3:0] $end
$var reg 1 H permutation_extend $end
$var reg 1 I permutation_start $end
$var reg 1 J pt_finish $end
$var reg 320 K pt_stemp [319:0] $end
$var reg 5 L round [4:0] $end
$var reg 4 M state [3:0] $end
$var reg 128 N tag_r [127:0] $end
$scope module permutation $end
$var wire 320 O S [319:0] $end
$var wire 1 ( clk $end
$var wire 5 P round [4:0] $end
$var wire 1 , rst $end
$var wire 1 I start $end
$var reg 320 Q S_out [319:0] $end
$var reg 5 R counter [4:0] $end
$var reg 1 7 fin $end
$var reg 3 S nst [2:0] $end
$var reg 3 T st [2:0] $end
$var reg 64 U x0 [63:0] $end
$var reg 64 V x0_ps [63:0] $end
$var reg 64 W x1 [63:0] $end
$var reg 64 X x1_ps [63:0] $end
$var reg 64 Y x2 [63:0] $end
$var reg 64 Z x2_pc [63:0] $end
$var reg 64 [ x2_ps [63:0] $end
$var reg 64 \ x3 [63:0] $end
$var reg 64 ] x3_ps [63:0] $end
$var reg 64 ^ x4 [63:0] $end
$var reg 64 _ x4_ps [63:0] $end
$var integer 32 ` i [31:0] $end
$upscope $end
$upscope $end
$upscope $end
$enddefinitions $end
#0
$dumpvars
bx `
bx _
bx ^
bx ]
bx \
bx [
bx Z
bx Y
bx X
bx W
bx V
bx U
bx T
bx S
bx R
bx Q
bx P
bx O
bx N
bx M
bx L
bx K
xJ
xI
xH
b0 G
bx F
xE
xD
bx C
bx B
xA
bx @
bx ?
bx >
bx =
b100000101010011010000110100111101001110100000000000000000000000 <
b110000101110011011000110110111101101110100000000000000000000000 ;
bx :
bx 9
bx 8
x7
bx 6
b1 5
b1 4
b110000101110011011000110110111101101110 3
b10001110101110110010100101011101101010000001110001110100101101011000001100000110110101001110100000110110001011100010001001000010 2
b10110111001000110100101001001101101110011111101110001011011111000010101010100101011100110101111010111110111100010001100000001100 1
bx 0
b100000101010011010000110100111101001110 /
bx .
0-
0,
b110000101110011011000110110111101101110 +
b10001110101110110010100101011101101010000001110001110100101101011000001100000110110101001110100000110110001011100010001001000010 *
b10110111001000110100101001001101101110011111101110001011011111000010101010100101011100110101111010111110111100010001100000001100 )
0(
b100000101010011010000110100111101001110 '
bx &
bx %
x$
bx #
bx "
bx !
$end
#5
b0 L
b0 P
b0 S
07
0$
b0 M
0I
0E
0A
0J
0H
0D
1(
#10
b0 8
b0 9
b0 #
b0 F
b0 &
b0 @
b0 "
b0 K
b0 !
b0 6
b0 N
b0 %
b0 0
b0 C
b0 >
b0 =
b0 O
b0 ?
b0 :
b0 Q
b0 V
b0 X
b0 [
b0 ]
b0 _
b0 U
b0 W
b0 Y
b0 \
b0 ^
b0 Z
0(
1,
#15
b0 B
b0 R
b0 T
1(
#20
b1 G
0(
0,
1-
#25
b1000000010000000000011000000100000000000000000000000000000000000 8
b1011011100100011010010100100110110111001111110111000101101111100001010101010010101110011010111101011111011110001000110000000110010001110101110110010100101011101101010000001110001110100101101011000001100000110110101001110100000110110001011100010001001000010 9
b1100 L
b1100 P
b10000000100000000000110000001000000000000000000000000000000000001011011100100011010010100100110110111001111110111000101101111100001010101010010101110011010111101011111011110001000110000000110010001110101110110010100101011101101010000001110001110100101101011000001100000110110101001110100000110110001011100010001001000010 ?
b1 M
1(
#30
0(
b0 .
0-
#35
b1 S
1I
b10000000100000000000110000001000000000000000000000000000000000001011011100100011010010100100110110111001111110111000101101111100001010101010010101110011010111101011111011110001000110000000110010001110101110110010100101011101101010000001110001110100101101011000001100000110110101001110100000110110001011100010001001000010 =
b10000000100000000000110000001000000000000000000000000000000000001011011100100011010010100100110110111001111110111000101101111100001010101010010101110011010111101011111011110001000110000000110010001110101110110010100101011101101010000001110001110100101101011000001100000110110101001110100000110110001011100010001001000010 O
1(
#40
0(
b1010 .
#45
b10 S
b1 T
1(
#50
0(
b10100 .
#55
b11 S
b1000000010000000000011000000100000000000000000000000000000000000 U
b1011011100100011010010100100110110111001111110111000101101111100 W
b10101010100101011100110101111010111110111100010001100000001100 Y
b1000111010111011001010010101110110101000000111000111010010110101 \
b1000001100000110110101001110100000110110001011100010001001000010 ^
b10 T
1(
#60
0(
b11110 .
#65
b100 S
b10101010100101011100110101111010111110111100010001100011111100 Z
b11 T
b1 R
1(
#70
0(
b101000 .
#75
b10 S
b1011001010011110000101100100101000100111110011011110110100001001 V
b1011111000011000101000111111001100100001110000011101110110001011 X
b110001101111101000100100100110011101110110101110110111000111101 [
b1000000111011110001001010111010011001001110001100010101110111 ]
b1011100110011100111111111011100000010111111000111101111111001011 _
b100 T
b1000000 `
1(
#80
0(
b110010 .
#85
b11 S
b1111001011100100001101111010100010000010000100001101011000001011 ^
b10111101000100010000100100001001010000110010011100011111011010 \
b10011101001110011011110010001110101010000001111000010010011011 Y
b1010100010011110001111111101000100111000101100110000000010010001 W
b111001111100001111100001000001011001100111001011100110101010010 U
b10 T
1(
#90
0(
b111100 .
#95
b100 S
b10011101001110011011110010001110101010000001111000010001111010 Z
b10 R
b11 T
1(
#100
0(
b1000110 .
#105
b10 S
b1010000010001111100110101010010111101111010110110110101100010101 [
b1111010100111010010011010011101111100010110110110001000101010001 _
b111001101111111110010100011001100101110001010101000111001100010 V
b111011011111101110101101100110110100000010111101110010110010 X
b111000000110001101001010001100001001100010010010101100100111000 ]
b100 T
b1000000 `
1(
#110
0(
b1010000 .
#115
b11 S
b1100101100100001010101000010100100111101111001000011101001010101 ^
b1001001010110001100100010110100111011000110101100110110101001010 \
b10011001001010011010011001110110001111010010111011001100110011 Y
b1100101101001010011110111010110101110000010010001000011001010111 W
b1100000000011011011000100111101111100000100100000100100010010101 U
b10 T
1(
#120
0(
b1011010 .
#125
b100 S
b10011001001010011010011001110110001111010010111011001111100001 Z
b11 T
b11 R
1(
#130
0(
b1100100 .
#135
b10 S
b1011011011101010101110101010111110010111010011011001000001101000 V
b1111011011000001110011001010011000100010111010111000110101111111 X
b101101111111111101010011100111100100101110111001101100001011100 [
b11010010011011111101010100101100011010101100010110101000101001 ]
b1001100111010000100011001110110111000101001110101101001100001000 _
b100 T
b1000000 `
1(
#140
0(
b1101110 .
#145
b11 S
b1111111000000001101100001001110110011010111111000100111011101000 ^
b101111000010010010011111101110110010110100100100101100101011 \
b11101101111100000111000111110001011101001011100011100010011 Y
b110010001010011111101000110111001010010110100110010100011001 W
b111000000111110101010101111100110101110101100111100100001111000 U
b10 T
1(
#150
0(
b1111000 .
#155
b100 S
b11101101111100000111000111110001011101001011100011111010000 Z
b100 R
b11 T
1(
#160
0(
b10000010 .
#165
b10 S
b1000000111010010111001010001001001001101101100000010100001101011 X
b111100000011001000001101000100111010111110101000110000010011010 V
b11011101100101111100110110110001011000101100111110110 [
b1111010101000011100111011110111111100010001111100110010011001010 _
b1111111000011010000001101111110111101111010000000110111100110010 ]
b100 T
b1000000 `
1(
#170
0(
b10001100 .
#175
b11 S
b1001011101011000000001011110011001011000100000001011100111001101 ^
b10100111100111111110111000101010011010001010100100010001001 \
b1101100000010110000001010100111010001011111000101100010001101010 Y
b1010101111011110101011011101000011110111001100101100111011111101 W
b1000100101001100010000000010110101110110100101010011001011111101 U
b10 T
1(
#180
0(
b10010110 .
#185
b100 S
b1101100000010110000001010100111010001011111000101100010011011110 Z
b11 T
b101 R
1(
#190
0(
b10100000 .
#195
b10 S
b1110000111111110101111110111010011010010111000100000010101000111 X
b1110100010100100010100100010000100000011000001011111100111011110 ]
b1111001110111010101111110011110001011101011110100010010011000 [
b111110110111010000101110100001011111100001100100011111010111011 V
b11001110101110010100101000011111011010111001111011010110001001 _
b100 T
b1000000 `
1(
#200
0(
b10101010 .
#205
b11 S
b110001000100100011111011111100000010001110010111010110111001011 ^
b110001111110001000011110110011110100010010101011011100100100010 \
b111000100110101001000010100101111010000010101100101101111000110 Y
b11110101110100000001101100011001010001100011101001000000110 W
b1111100101001110100100110100001001100101011110110001010100010010 U
b10 T
1(
#210
0(
b10110100 .
#215
b100 S
b111000100110101001000010100101111010000010101100101101101100011 Z
b110 R
b11 T
1(
#220
0(
b10111110 .
#225
b10 S
b1000111101000100010100100100110011101101100110001001110010011110 ]
b1110111000101010101111010110011001011101011010011110011101010111 V
b10101010001011100101101111100111001100111110101011011101111 _
b1110110110110101010000010000010100001110110101110101001110111100 X
b1000100101100000001011101111010011110100000100100111001001010011 [
b100 T
b1000000 `
1(
#230
0(
b11001000 .
#235
b11 S
b1011010011000111000111111001000111110000011011101100000011111011 ^
b1110011010101000110001001111101001010111100001011000110001110101 \
b1111110101101110010011010101011101110010110000001010110011 Y
b1000101000000010111001111000101000000001101101101010010011011001 W
b10001011110001101011101110111101000011011101111101010011111 U
b10 T
1(
#240
0(
b11010010 .
#245
b100 S
b1111110101101110010011010101011101110010110000001000100101 Z
b11 T
b111 R
1(
#250
0(
b11011100 .
#255
b10 S
b1110100100000001001011001001000011100010000101001111000001010111 V
b101100001101101000111101110100110100110010111011100100000010111 _
b101110101100110010101011011001101000110011111111001010010011000 X
b110011001001111101110100100000100000011111010000001100110001001 [
b1101111110001000101000010100000010110011100100100101100001100011 ]
b100 T
b1000000 `
1(
#260
0(
b11100110 .
#265
b11 S
b1000001110111010100011000001111110101111010100010100001000 ^
b1110101101001110101011001010110010110011000111101110010100111100 \
b1111000011110001010110011000100010000110000100111011010100101011 Y
b1101000011011000000001110000000001000101001110011111110011110001 W
b101011001000100110101001100111001010111100101000010010100011011 U
b10 T
1(
#270
0(
b11110000 .
#275
b100 S
b1111000011110001010110011000100010000110000100111011010110101100 Z
b1000 R
b11 T
1(
#280
0(
b11111010 .
#285
b10 S
b1110110111011001000011110101000100010100110000101110111001011 V
b110111111110101110000010101001011011110000001100011100111001110 X
b1101111111010110111000110110011101110000011101001011011010100010 [
b1101111101101101100010000101011000011100100111011110110001100010 ]
b110100111010000010001111001110010001001101100110011110011010100 _
b100 T
b1000000 `
1(
#290
0(
b100000100 .
#295
b11 S
b111101000111001111101000110111011010100101001011001010001110 ^
b11000111101011001111001000001011001101001100011100010101010111 \
b11101101000010110010010101100101010101100011110011111100101001 Y
b1011010111100111110001111011011110110010111010000001110000111111 W
b11111110000111100111101110110010011101000101110000011100111010 U
b10 T
1(
#300
0(
b100001110 .
#305
b100 S
b11101101000010110010010101100101010101100011110011111101010001 Z
b11 T
b1001 R
1(
#310
0(
b100011000 .
#315
b10 S
b1011111001101101010111111001111010111000011111000100111011011010 X
b1011101110001011010001011001100110100111110011010111111111010010 _
b1000000101001011111011011011000010100101010010011110100100100110 V
b111111101011110111100110001110000001010000111001110111000011001 [
b1011000100001010100100000000000101111000110100000101010010010101 ]
b100 T
b1000000 `
1(
#320
0(
b100100010 .
#325
b11 S
b1101001000101111101101011010110101111101110111110010000010001111 ^
b1011111000101100000010100010000000110000100011101101110011101000 \
b1010010100001100111100010101111001111111001110101110101010101101 Y
b111000001110111010110111111011011001110111000101110001010110000 W
b1110100011110001101011111111000111001100010000010010011010000101 U
b10 T
1(
#330
0(
b100101100 .
#335
b100 S
b1010010100001100111100010101111001111111001110101110101011000100 Z
b1010 R
b11 T
1(
#340
0(
b100110110 .
#345
b10 S
b1110010110100101111000011010001001001110011000100011100001110110 X
b11100110001000000101010101010101111100100010011111011010010011 ]
b1001001111110100010001000111101110000011101101110001001010011001 V
b110101010000111111000001101101000000011011101101101011110001100 [
b10110000100010111111100010111100000011001100010001110011010111 _
b100 T
b1000000 `
1(
#350
0(
b101000000 .
#355
b11 S
b1001010111111011001000110101110100110110101000010110111110010001 ^
b110011000001111111010111001010000100011011111000110101010101010 \
b110111001101110000011110011010001101010110000000110011100010100 Y
b1000110000010110001010001100000011010000101110001011000000000010 W
b100101011010110010111111001110000110100011111000010010101010111 U
b10 T
1(
#360
0(
b101001010 .
#365
b100 S
b110111001101110000011110011010001101010110000000110011101001110 Z
b11 T
b1011 R
1(
#370
0(
b101010100 .
#375
b10 S
b1100110001110111110000010100110001111100001011111001000110011 ]
b100111010100011101100110011110011101101011000001011100010110001 V
b11010101010100100110110011010111111001001000011001010100101010 X
b1111001111100110110010001100100111000101111111011011010100111011 _
b1000110001110111110110000100001001010001000001100010110110100010 [
b100 T
b1000000 `
1(
#380
0(
b101011110 .
#385
b11 S
b1110000011100011111110111000001011001011100011111011110100110101 ^
b110110001010001000101110101000011111001111100101101010010001101 \
b100000001111101111010110000001001110000110000010010001111000101 Y
b1111010000000010000000011011000001100100010001111001010101001101 W
b1000111110111110000100011111110001110001001111000001011011010011 U
b10 T
1(
#390
0(
b101101000 .
#395
b100 S
b100000001111101111010110000001001110000110000010010001110001110 Z
b1100 R
b11 T
1(
#400
0(
b101110010 .
#405
b101 S
b111001110010000111011010010111011011100000010101111010011010101 V
b1100101100100010111111011100111111101001011101000110000000001100 [
b1110010110000111011010101001001110110001110010111110110110001 _
b1101001100100010000101001000110000100111000001000101110000100101 X
b11101111000001000101110100110001100111111110111100100100111000 ]
b100 T
b1000000 `
1(
#410
0(
b101111100 .
#415
b0 S
b1101011110110010100100000011011000001010010110110101011100111100 ^
b1001000101010011111110101110100100111111010001000000010000110111 \
b1001110110011111000010001101111100100010011010111000000110001010 Y
b101001001111100101110000101010101010100100000001111100100100010 W
b1110110110100101000011100000101111111000101000011111110110111001 U
b101 T
1(
#420
0(
b110000110 .
