permutation/permutation.v
module permutation (
    input              clk,
    input              rst,
    input      [319:0] S,
    input      [4:0]   round,
    input              start,
    output reg [319:0] S_out,
    output reg         fin  
);

reg [63:0] x0, x1, x2, x3, x4;
reg [63:0] x2_pc;
reg [63:0] x0_ps, x1_ps, x2_ps, x3_ps, x4_ps;
reg [4:0] counter;
integer i;

// FSM
reg [2:0]st, nst;
parameter IDLE = 'd0;
parameter IN   = 'd1;
parameter PC   = 'd2;
parameter PS   = 'd3;
parameter PL   = 'd4;
parameter OUT  = 'd5;

always @(posedge clk) begin
    if (rst) st <= IDLE;
    else     st <= nst;
end

always @(*) begin
    case(st) 
        IDLE: nst = (start)?IN:IDLE;
        IN:   nst = PC;
        PC:   nst = PS;
        PS:   nst = PL;
        PL:   nst = (counter==round)? OUT : PC ;
        OUT:  nst = IN;
        default: nst = IN;
    endcase
end

wire [63:0] Cr [11:0];
    assign Cr[0] = 64'hf0;
    assign Cr[1] = 64'he1;
    assign Cr[2] = 64'hd2;
    assign Cr[3] = 64'hc3;
    assign Cr[4] = 64'hb4;
    assign Cr[5] = 64'ha5;
    assign Cr[6] = 64'h96;
    assign Cr[7] = 64'h87;
    assign Cr[8] = 64'h78;
    assign Cr[9] = 64'h69;
    assign Cr[10] = 64'h5a;
    assign Cr[11] = 64'h4b;
wire [4:0] const[31:0];
    assign const[0]  = 5'h4;
    assign const[1]  = 5'hb;
    assign const[2]  = 5'h1f;
    assign const[3]  = 5'h14;
    assign const[4]  = 5'h1a;
    assign const[5]  = 5'h15;
    assign const[6]  = 5'h9;
    assign const[7]  = 5'h2;
    assign const[8]  = 5'h1b;
    assign const[9]  = 5'h5;
    assign const[10] = 5'h8;
    assign const[11] = 5'h12;
    assign const[12] = 5'h1d;
    assign const[13] = 5'h3;
    assign const[14] = 5'h6;
    assign const[15] = 5'h1c;
    assign const[16] = 5'h1e;
    assign const[17] = 5'h13;
    assign const[18] = 5'h7;
    assign const[19] = 5'he;
    assign const[20] = 5'h0;
    assign const[21] = 5'hd;
    assign const[22] = 5'h11;
    assign const[23] = 5'h18;
    assign const[24] = 5'h10;
    assign const[25] = 5'hc;
    assign const[26] = 5'h1;
    assign const[27] = 5'h19;
    assign const[28] = 5'h16;
    assign const[29] = 5'ha;
    assign const[30] = 5'hf;
    assign const[31] = 5'h17;


always @(posedge clk or posedge rst) begin
    if (rst) begin
        {x0, x1, x2, x3, x4, x2_pc} <= 64'd0;
        {x0_ps, x1_ps, x2_ps, x3_ps, x4_ps} <= 64'd0;
        S_out <= 320'd0;
        counter <= 5'd0;
    end 

    else if (st==IN) begin
        {x0, x1, x2, x3, x4} <= S; // S = x0 || x1 || x2 || x3 || x4 //將Ｓ拆分成多個訊號，自動定義等長 
        {x0_ps, x1_ps, x2_ps, x3_ps, x4_ps} <= 64'd0;
    end
    

    // Addition of Constants
    else if (st==PC) begin
        //if (round == 6)      x2_pc <= x2 ^ (8'h96 - (counter - 1'd1) * 4'd15);
        //else if (round == 8) x2_pc <= x2 ^ (8'hb4 - (counter - 1'd1) * 4'd15);
        //else                 x2_pc <= x2 ^ (8'hf0 - (counter - 1'd1) * 4'd15);
        if (round == 5'd12)     x2_pc <= x2 ^ Cr[counter];
        else if (round == 5'd8) x2_pc <= x2 ^ Cr[counter+5'd4];
        else if (round == 5'd6) x2_pc <= x2 ^ Cr[counter+5'd6];
        else x2_pc <= x2;
        counter <= counter +1'd1;
    end

    // Substitution Layer
    else if (st==PS) begin
        for (i=0;i<64;i=i+1) begin
            {x0_ps[i], x1_ps[i], x2_ps[i], x3_ps[i], x4_ps[i]} <= const[{x0[i], x1[i], x2_pc[i], x3[i], x4[i]}];
        end
    end

    // Linear Diffusion Layer 環狀
    else if (st == PL) begin
    x0 <= x0_ps ^ (x0_ps >> 19) ^ (x0_ps >> 28) ^ (x0_ps << (64 - 19)) ^ (x0_ps << (64 - 28));
    x1 <= x1_ps ^ (x1_ps >> 61) ^ (x1_ps >> 39) ^ (x1_ps << (64 - 61)) ^ (x1_ps << (64 - 39));
    x2 <= x2_ps ^ (x2_ps >> 1)  ^ (x2_ps >> 6)  ^ (x2_ps << (64 - 1))  ^ (x2_ps << (64 - 6));
    x3 <= x3_ps ^ (x3_ps >> 10) ^ (x3_ps >> 17) ^ (x3_ps << (64 - 10)) ^ (x3_ps << (64 - 17));
    x4 <= x4_ps ^ (x4_ps >> 7)  ^ (x4_ps >> 41) ^ (x4_ps << (64 - 7))  ^ (x4_ps << (64 - 41));
    end
    else if (st==OUT) begin
        S_out <= {x0, x1, x2, x3, x4};
    end
    else begin
        x0 <= x0;
        x1 <= x1;
        x2 <= x2;
        x3 <= x3;
        x4 <= x4;
        x2_pc <= x2_pc;
        x0_ps <= x0_ps;
        x1_ps <= x1_ps;
        x2_ps <= x2_ps;
        x3_ps <= x3_ps;
        x4_ps <= x4_ps;
        counter <= counter;
    end
end

// signal done
always @(posedge clk or posedge rst) begin
    if (rst) fin <=1'd0;
    else if (st==OUT) fin <=1'd1;
    else fin <=1'd0;
end


endmodule

permutation/permutation_tb.v
`timescale 1ns/1ns

module tb_permutation;

    reg clk;
    reg rst;
    reg [319:0] S;
    reg [4:0] round;
    reg start;
    wire [319:0] S_out;

    // Instantiate the permutation module
    permutation uut (
        .clk(clk),
        .rst(rst),
        .S(S),
        .round(round),
        .start(start),
        .S_out(S_out)
    );

    // Clock generation
    initial begin
        clk = 0;
        forever #5 clk = ~clk; // 10 ns period
    end

    // Test sequence
    initial begin
        // Initialize signals
        rst = 1;
        start = 0;
        S = 320'b0;
        round = 5'd0;

        // Reset the system
        #20 rst = 0;

        // Test Case 1: Provide initial values and start the permutation
        #10;
        S = {64'd9241399655273594880, 64'd45400375717294337, 64'd16688268966856064344, 64'd3724962908607778966, 64'd5511705892194216375};
        round = 5'd6; // Set the round count
        start = 1;

        #10 start = 0; // De-assert start signal
        #40 S = 320'd0;

        // Wait for completion (assuming the permutation takes multiple cycles)
        #500;

        // Check the final state
        if (S_out === 320'hdbfa7de9557bfe77cd1ee5a28bf38302ddaaba10f9bbc338f08f66dfae56028e3c3fa37c30f578a4) begin
            $display("Test Passed: Final State is correct.");
            $display("Final State: %h", S_out);
            $display("X0: %h", S_out[319:256]);
            $display("X1: %h", S_out[255:192]);
            $display("X2: %h", S_out[191:128]);
            $display("X3: %h", S_out[127:64]);
            $display("X4: %h", S_out[63:0]);
        end else begin
            $display("Test Failed: Final State is incorrect.");
            $display("Actual Final State: %h", S_out);
        end

        // End simulation
        $finish;
    end

    // Generate VCD file for waveform
    initial begin
        $dumpfile("permutation.vcd");
        $dumpvars(0, tb_permutation);
    end

endmodule

permutation/permutation.vcd
$date
	Mon Jan 20 20:51:17 2025
$end
$version
	Icarus Verilog
$end
$timescale
	1ns
$end
$scope module tb_permutation $end
$var wire 320 ! S_out [319:0] $end
$var reg 320 " S [319:0] $end
$var reg 1 # clk $end
$var reg 5 $ round [4:0] $end
$var reg 1 % rst $end
$var reg 1 & start $end
$scope module uut $end
$var wire 320 ' S [319:0] $end
$var wire 1 # clk $end
$var wire 5 ( round [4:0] $end
$var wire 1 % rst $end
$var wire 1 & start $end
$var reg 320 ) S_out [319:0] $end
$var reg 5 * counter [4:0] $end
$var reg 1 + fin $end
$var reg 3 , nst [2:0] $end
$var reg 3 - st [2:0] $end
$var reg 64 . x0 [63:0] $end
$var reg 64 / x0_ps [63:0] $end
$var reg 64 0 x1 [63:0] $end
$var reg 64 1 x1_ps [63:0] $end
$var reg 64 2 x2 [63:0] $end
$var reg 64 3 x2_pc [63:0] $end
$var reg 64 4 x2_ps [63:0] $end
$var reg 64 5 x3 [63:0] $end
$var reg 64 6 x3_ps [63:0] $end
$var reg 64 7 x4 [63:0] $end
$var reg 64 8 x4_ps [63:0] $end
$var integer 32 9 i [31:0] $end
$upscope $end
$upscope $end
$enddefinitions $end
#0
$dumpvars
bx 9
b0 8
b0 7
b0 6
b0 5
b0 4
b0 3
b0 2
b0 1
b0 0
b0 /
b0 .
bx -
b1 ,
0+
b0 *
b0 )
b0 (
b0 '
0&
1%
b0 $
0#
b0 "
b0 !
$end
#5
b0 ,
b0 -
1#
#10
0#
#15
1#
#20
0#
0%
#25
1#
#30
b1 ,
0#
1&
b110 $
b110 (
b10000000010000000000110000000110000000000000000000000000000000000000000010100001010010110110011010110011010011000111000100000001111001111001100010100100001101010000010110100001011111010101100000110011101100011011101000000111100110010001001010010000100101100100110001111101100000110100111010000010101010011110100110110111 "
b10000000010000000000110000000110000000000000000000000000000000000000000010100001010010110110011010110011010011000111000100000001111001111001100010100100001101010000010110100001011111010101100000110011101100011011101000000111100110010001001010010000100101100100110001111101100000110100111010000010101010011110100110110111 '
#35
b10 ,
b1 -
1#
#40
0#
0&
#45
b11 ,
b1000000001000000000011000000011000000000000000000000000000000000 .
b10100001010010110110011010110011010011000111000100000001 0
b1110011110011000101001000011010100000101101000010111110101011000 2
b11001110110001101110100000011110011001000100101001000010010110 5
b100110001111101100000110100111010000010101010011110100110110111 7
b10 -
1#
#50
0#
#55
b100 ,
b1 *
b1110011110011000101001000011010100000101101000010111110111001110 3
b11 -
1#
#60
0#
#65
b10 ,
b101010001101001010100100011011010101100111101111000110001011000 /
b11101100000100011100000011101100111100010101100000010001101000 1
b1100011110101110100100001110010101101010101100111010111101110 6
b101010010001010000100011110010001001011101110111001101000010001 4
b111111101001100011110010110111100101010111111110110100100100001 8
b100 -
b1000000 9
1#
#70
0#
#75
b11 ,
b1000101000100111100111100010100101100100000101010011000111001111 7
b101100110000100111000110001001011000011011100110111011011011000 5
b1011101110011101001100010101000111111111010010001011100101110001 2
b1001010101011111010111011110101000001110100100000010111111001001 0
b110101010011010100111010011111011000000001001000111101010101100 .
b10 -
1#
#80
0#
b0 "
b0 '
#85
b100 ,
b10 *
b1011101110011101001100010101000111111111010010001011100111110110 3
b11 -
1#
#90
0#
#95
b10 ,
b111001100110111111011110110001011001110010101001010001011100 1
b110011011100000000101101010111111000100111111011100011001010 /
b101001100011110100011110110110100101010001000110110100011000111 4
b1101010101111001100100011000010000010110101111101110100110000000 6
b1100011011100001001000011101001110101101111001100110001110011111 8
b100 -
b1000000 9
1#
#100
0#
#105
b11 ,
b1000010111010000100001010000111000101010111101101111111001000 7
b1100000110001100101001010101110010111111011110010100110101100101 5
b1110011111011101101100101110011000001011100110100101000100000111 2
b1010010111100010100001111010011000101111100000101111101101000111 0
b111001000111110110011111110111010110101000001010010101010000110 .
b10 -
1#
#110
0#
#115
b100 ,
b11 *
b1110011111011101101100101110011000001011100110100101000101111111 3
b11 -
1#
#120
0#
#125
b10 ,
b111010011001101010110100101001000000101111001000110110111011010 /
b10011111011111010001011010111000100101000000100101101110100 1
b1010110111110010110110100001111010011011111000011100011101001111 4
b1011000100000001110010101011111111011011001111110001000010010111 6
b101010001010100101101010101110101110101101001111001100010101100 8
b100 -
b1000000 9
1#
#130
0#
#135
b11 ,
b1010001001000110110011111111101110011001011001101111110111000111 7
b1110010100110010100100100110110010001100101100011001011001100 5
b100010110111100011111000111100110101100011111101010001111110101 2
b100100010101101111011011000110100001001101010111110011100000101 0
b1010011100110000110010010110110011100010011110111000100001000110 .
b10 -
1#
#140
0#
#145
b100 ,
b100 *
b100010110111100011111000111100110101100011111101010001110011100 3
b11 -
1#
#150
0#
#155
b10 ,
b1111011000001111011000100101100111010111000110110011100000010110 /
b101100001101101101110010110001111000110111000001010000001011000 1
b101000010101110111000111011100101010010010010100111011001100101 4
b1011001011100001010011000000101001001111001011101000101111010110 6
b1111011001101001011101001011111000001000010100100100110100001111 8
b100 -
b1000000 9
1#
#160
0#
#165
b11 ,
b1011011010000001100011110111000111110011101110011101110100101111 7
b1010100110101011010010100111101011101110000110011111100011 5
b110110110111011001010011110101100011110001001100110010010001110 2
b101110010001101101100110011110101000001010101010111100111101000 0
b1110000010111110001111011111011101011011101001100010011101101000 .
b10 -
1#
#170
0#
#175
b100 ,
b101 *
b110110110111011001010011110101100011110001001100110010011010100 3
b11 -
1#
#180
0#
#185
b10 ,
b10100100000000001011000101000001010111111000001110010101111000 1
b111101011001000011001110111100110110000100011010111101011001111 4
b1100010110001001101001010010100100000100110101001010001011010000 6
b1100101110101010100110010010010111101111011111000100010100110111 /
b1011110010100111001000110110000101011001010000011011101101100100 8
b100 -
b1000000 9
1#
#190
0#
#195
b11 ,
b1100010101110010110011011111101000101001101011010110101110000011 7
b10000011010000101001011000010010011100000000010001010110010010 5
b1111101001000111011101010101100010001110000010011111001001000011 2
b1100000110101110100011110001100000011000101101011100111011100001 0
b1011010011001000001100110010110000000110111100010110101010000110 .
b10 -
1#
#200
0#
#205
b100 ,
b110 *
b1111101001000111011101010101100010001110000010011111001000001000 3
b11 -
1#
#210
0#
#215
b101 ,
b100110100010011011100010101001000111011111010100100010111 4
b1000101001000101000001000000101010111001111000001111111011111110 1
b1100111000000011100000010011111000100001010000010100001001111110 6
b10111001011101111001111110000000001100010110011000000111111100 /
b110010110100110011010010111011010100101000011011011000011110001 8
b100 -
b1000000 9
1#
#220
0#
#225
b1 ,
b11110000111111101000110111110000110000111101010111100010100100 7
b1111000010001111011001101101111110101110010101100000001010001110 5
b1101110110101010101110100001000011111001101110111100001100111000 2
b1100110100011110111001011010001010001011111100111000001100000010 0
b1101101111111010011111011110100101010101011110111111111001110111 .
b101 -
1#
#230
0#
#235
b10 ,
b11011011111110100111110111101001010101010111101111111110011101111100110100011110111001011010001010001011111100111000001100000010110111011010101010111010000100001111100110111011110000110011100011110000100011110110011011011111101011100101011000000010100011100011110000111111101000110111110000110000111101010111100010100100 !
b11011011111110100111110111101001010101010111101111111110011101111100110100011110111001011010001010001011111100111000001100000010110111011010101010111010000100001111100110111011110000110011100011110000100011110110011011011111101011100101011000000010100011100011110000111111101000110111110000110000111101010111100010100100 )
1+
b1 -
1#
#240
0#
#245
b11 ,
0+
b0 /
b0 1
b0 4
b0 6
b0 8
b0 .
b0 0
b0 2
b0 5
b0 7
b10 -
1#
#250
0#
#255
b100 ,
b111 *
bx 3
b11 -
1#
#260
0#
#265
b10 ,
bx /
bx 1
bx 4
bx 6
bx 8
b100 -
b1000000 9
1#
#270
0#
#275
b11 ,
bx 7
bx 5
bx 2
bx 0
bx .
b10 -
1#
#280
0#
#285
b100 ,
b1000 *
b11 -
1#
#290
0#
#295
b10 ,
b100 -
b1000000 9
1#
#300
0#
#305
b11 ,
b10 -
1#
#310
0#
#315
b100 ,
b1001 *
b11 -
1#
#320
0#
#325
b10 ,
b100 -
b1000000 9
1#
#330
0#
#335
b11 ,
b10 -
1#
#340
0#
#345
b100 ,
b1010 *
b11 -
1#
#350
0#
#355
b10 ,
b100 -
b1000000 9
1#
#360
0#
#365
b11 ,
b10 -
1#
#370
0#
#375
b100 ,
b1011 *
b11 -
1#
#380
0#
#385
b10 ,
b100 -
b1000000 9
1#
#390
0#
#395
b11 ,
b10 -
1#
#400
0#
#405
b100 ,
b1100 *
b11 -
1#
#410
0#
#415
b10 ,
b100 -
b1000000 9
1#
#420
0#
#425
b11 ,
b10 -
1#
#430
0#
#435
b100 ,
b1101 *
b11 -
1#
#440
0#
#445
b10 ,
b100 -
b1000000 9
1#
#450
0#
#455
b11 ,
b10 -
1#
#460
0#
#465
b100 ,
b1110 *
b11 -
1#
#470
0#
#475
b10 ,
b100 -
b1000000 9
1#
#480
0#
#485
b11 ,
b10 -
1#
#490
0#
#495
b100 ,
b1111 *
b11 -
1#
#500
0#
#505
b10 ,
b100 -
b1000000 9
1#
#510
0#
#515
b11 ,
b10 -
1#
#520
0#
#525
b100 ,
b10000 *
b11 -
1#
#530
0#
#535
b10 ,
b100 -
b1000000 9
1#
#540
0#
#545
b11 ,
b10 -
1#
#550
0#
#555
b100 ,
b10001 *
b11 -
1#
#560
0#
#565
b10 ,
b100 -
b1000000 9
1#
#570
0#
#575
b11 ,
b10 -
1#
